WuaiPojieLuntanjinghuaJi2018DisiBufen/README.md
WuaiPojieLuntanjinghuaJi2018DisiBufen/__init__.py
WuaiPojieLuntanjinghuaJi2018DisiBufen/__main__.py
WuaiPojieLuntanjinghuaJi2018DisiBufen/file.epub
WuaiPojieLuntanjinghuaJi2018DisiBufen/index.html
WuaiPojieLuntanjinghuaJi2018DisiBufen/css/__init__.py
WuaiPojieLuntanjinghuaJi2018DisiBufen/css/annotations.css
WuaiPojieLuntanjinghuaJi2018DisiBufen/css/main.css
WuaiPojieLuntanjinghuaJi2018DisiBufen/css/normalize.css
WuaiPojieLuntanjinghuaJi2018DisiBufen/css/popup.css
WuaiPojieLuntanjinghuaJi2018DisiBufen/font/__init__.py
WuaiPojieLuntanjinghuaJi2018DisiBufen/font/fontello.eot
WuaiPojieLuntanjinghuaJi2018DisiBufen/font/fontello.svg
WuaiPojieLuntanjinghuaJi2018DisiBufen/font/fontello.ttf
WuaiPojieLuntanjinghuaJi2018DisiBufen/font/fontello.woff
WuaiPojieLuntanjinghuaJi2018DisiBufen/img/__init__.py
WuaiPojieLuntanjinghuaJi2018DisiBufen/img/annotator-glyph-sprite.png
WuaiPojieLuntanjinghuaJi2018DisiBufen/img/annotator-icon-sprite.png
WuaiPojieLuntanjinghuaJi2018DisiBufen/img/apple-touch-icon.png
WuaiPojieLuntanjinghuaJi2018DisiBufen/img/cancelfullscreen.png
WuaiPojieLuntanjinghuaJi2018DisiBufen/img/close.png
WuaiPojieLuntanjinghuaJi2018DisiBufen/img/fullscreen.png
WuaiPojieLuntanjinghuaJi2018DisiBufen/img/loader.gif
WuaiPojieLuntanjinghuaJi2018DisiBufen/img/menu-icon.png
WuaiPojieLuntanjinghuaJi2018DisiBufen/img/save.png
WuaiPojieLuntanjinghuaJi2018DisiBufen/img/saved.png
WuaiPojieLuntanjinghuaJi2018DisiBufen/img/settings-s.png
WuaiPojieLuntanjinghuaJi2018DisiBufen/img/settings.png
WuaiPojieLuntanjinghuaJi2018DisiBufen/img/star.png
WuaiPojieLuntanjinghuaJi2018DisiBufen/js/__init__.py
WuaiPojieLuntanjinghuaJi2018DisiBufen/js/epub.js
WuaiPojieLuntanjinghuaJi2018DisiBufen/js/epub.min.js
WuaiPojieLuntanjinghuaJi2018DisiBufen/js/epub.min.map
WuaiPojieLuntanjinghuaJi2018DisiBufen/js/hooks.min.js
WuaiPojieLuntanjinghuaJi2018DisiBufen/js/hooks.min.map
WuaiPojieLuntanjinghuaJi2018DisiBufen/js/reader.js
wuai_pojie_luntanjinghua_ji_2018_disi_bufen-2024.3.5.0.dist-info/METADATA
wuai_pojie_luntanjinghua_ji_2018_disi_bufen-2024.3.5.0.dist-info/WHEEL
wuai_pojie_luntanjinghua_ji_2018_disi_bufen-2024.3.5.0.dist-info/entry_points.txt
wuai_pojie_luntanjinghua_ji_2018_disi_bufen-2024.3.5.0.dist-info/top_level.txt
wuai_pojie_luntanjinghua_ji_2018_disi_bufen-2024.3.5.0.dist-info/RECORD
